ehtplot/__init__.py
ehtplot/api.py
ehtplot/figure.py
ehtplot/helpers.py
ehtplot/layouts.py
ehtplot/panel.py
ehtplot/visual.py
ehtplot/color/__init__.py
ehtplot/color/cmap.py
ehtplot/color/cmath.py
ehtplot/color/core.py
ehtplot/color/ctab.py
ehtplot/color/eht.py
ehtplot/color/merge.py
ehtplot/color/modify.py
ehtplot/color/ctabs/Blues_lu.ctab
ehtplot/color/ctabs/Blues_lus.ctab
ehtplot/color/ctabs/Blues_u.ctab
ehtplot/color/ctabs/Blues_us.ctab
ehtplot/color/ctabs/BrBG_lu.ctab
ehtplot/color/ctabs/BrBG_lus.ctab
ehtplot/color/ctabs/BrBG_u.ctab
ehtplot/color/ctabs/BrBG_us.ctab
ehtplot/color/ctabs/BuGn_lu.ctab
ehtplot/color/ctabs/BuGn_lus.ctab
ehtplot/color/ctabs/BuGn_u.ctab
ehtplot/color/ctabs/BuGn_us.ctab
ehtplot/color/ctabs/BuPu_lu.ctab
ehtplot/color/ctabs/BuPu_lus.ctab
ehtplot/color/ctabs/BuPu_u.ctab
ehtplot/color/ctabs/BuPu_us.ctab
ehtplot/color/ctabs/GnBu_lu.ctab
ehtplot/color/ctabs/GnBu_lus.ctab
ehtplot/color/ctabs/GnBu_u.ctab
ehtplot/color/ctabs/GnBu_us.ctab
ehtplot/color/ctabs/Greens_lu.ctab
ehtplot/color/ctabs/Greens_lus.ctab
ehtplot/color/ctabs/Greens_u.ctab
ehtplot/color/ctabs/Greens_us.ctab
ehtplot/color/ctabs/Greys_lu.ctab
ehtplot/color/ctabs/Greys_lus.ctab
ehtplot/color/ctabs/Greys_u.ctab
ehtplot/color/ctabs/Greys_us.ctab
ehtplot/color/ctabs/OrRd_lu.ctab
ehtplot/color/ctabs/OrRd_lus.ctab
ehtplot/color/ctabs/OrRd_u.ctab
ehtplot/color/ctabs/OrRd_us.ctab
ehtplot/color/ctabs/Oranges_lu.ctab
ehtplot/color/ctabs/Oranges_lus.ctab
ehtplot/color/ctabs/Oranges_u.ctab
ehtplot/color/ctabs/Oranges_us.ctab
ehtplot/color/ctabs/PRGn_lu.ctab
ehtplot/color/ctabs/PRGn_lus.ctab
ehtplot/color/ctabs/PRGn_u.ctab
ehtplot/color/ctabs/PRGn_us.ctab
ehtplot/color/ctabs/PiYG_lu.ctab
ehtplot/color/ctabs/PiYG_lus.ctab
ehtplot/color/ctabs/PiYG_u.ctab
ehtplot/color/ctabs/PiYG_us.ctab
ehtplot/color/ctabs/PuBuGn_lu.ctab
ehtplot/color/ctabs/PuBuGn_lus.ctab
ehtplot/color/ctabs/PuBuGn_u.ctab
ehtplot/color/ctabs/PuBuGn_us.ctab
ehtplot/color/ctabs/PuBu_lu.ctab
ehtplot/color/ctabs/PuBu_lus.ctab
pyehtplot-0.9.0.dist-info/LICENSE
pyehtplot-0.9.0.dist-info/METADATA
pyehtplot-0.9.0.dist-info/WHEEL
pyehtplot-0.9.0.dist-info/top_level.txt
pyehtplot-0.9.0.dist-info/RECORD
