Metadata-Version: 2.1
Name: pyehtplot
Version: 0.9.0
Summary: Plotting functions for EHT
Home-page: https://github.com/liamedeiros/ehtplot
Author: Lia Medeiros
Author-email: lia2@uwm.edu
License: GPLv3+
Keywords: astronomy plotting
Classifier: Development Status :: 1 - Planning
Classifier: Intended Audience :: Science/Research
Classifier: Topic :: Scientific/Engineering :: Astronomy
Classifier: Topic :: Scientific/Engineering :: Physics
Classifier: Topic :: Scientific/Engineering :: Visualization
Classifier: License :: OSI Approved :: GNU General Public License v3 or later (GPLv3+)
Classifier: Programming Language :: Python :: 3
License-File: LICENSE
Requires-Dist: matplotlib
Requires-Dist: numpy
Requires-Dist: scipy
Requires-Dist: scikit-image
